{
  "reflection": [
    {
      "type": "ch.qos.logback.classic.BasicConfigurator",
      "methods": [
        {
          "name": "<init>",
          "parameterTypes": []
        }
      ]
    },
    {
      "type": "ch.qos.logback.classic.joran.SerializedModelConfigurator",
      "methods": [
        {
          "name": "<init>",
          "parameterTypes": []
        }
      ]
    },
    {
      "type": "ch.qos.logback.classic.spi.LogbackServiceProvider"
    },
    {
      "type": "ch.qos.logback.classic.util.DefaultJoranConfigurator",
      "methods": [
        {
          "name": "<init>",
          "parameterTypes": []
        }
      ]
    },
    {
      "type": "java.io.FilePermission"
    },
    {
      "type": "java.lang.RuntimePermission"
    },
    {
      "type": "java.lang.Thread",
      "fields": [
        {
          "name": "threadLocalRandomProbe"
        }
      ]
    },
    {
      "type": "java.net.NetPermission"
    },
    {
      "type": "java.net.SocketPermission"
    },
    {
      "type": "java.net.URLPermission",
      "methods": [
        {
          "name": "<init>",
          "parameterTypes": [
            "java.lang.String",
            "java.lang.String"
          ]
        }
      ]
    },
    {
      "type": "java.security.AllPermission"
    },
    {
      "type": "java.security.SecurityPermission"
    },
    {
      "type": "java.util.PropertyPermission"
    },
    {
      "type": "java.util.concurrent.atomic.AtomicBoolean",
      "fields": [
        {
          "name": "value"
        }
      ]
    },
    {
      "type": "java.util.concurrent.atomic.Striped64",
      "fields": [
        {
          "name": "base"
        },
        {
          "name": "cellsBusy"
        }
      ]
    },
    {
      "type": "javax.smartcardio.CardPermission"
    },
    {
      "type": "org.apache.mina.transport.socket.nio.NioProcessor",
      "methods": [
        {
          "name": "<init>",
          "parameterTypes": [
            "java.util.concurrent.Executor"
          ]
        }
      ]
    },
    {
      "type": "sun.security.provider.DRBG",
      "methods": [
        {
          "name": "<init>",
          "parameterTypes": [
            "java.security.SecureRandomParameters"
          ]
        }
      ]
    },
    {
      "type": "sun.security.provider.MD5",
      "methods": [
        {
          "name": "<init>",
          "parameterTypes": []
        }
      ]
    },
    {
      "type": "sun.security.provider.SHA",
      "methods": [
        {
          "name": "<init>",
          "parameterTypes": []
        }
      ]
    },
    {
      "type": "sun.security.provider.SHA2$SHA256",
      "methods": [
        {
          "name": "<init>",
          "parameterTypes": []
        }
      ]
    }
  ],
  "resources": [
    {
      "glob": "META-INF/services/ch.qos.logback.classic.spi.Configurator"
    },
    {
      "glob": "META-INF/services/java.lang.System$LoggerFinder"
    },
    {
      "glob": "META-INF/services/java.net.spi.InetAddressResolverProvider"
    },
    {
      "glob": "META-INF/services/java.nio.channels.spi.SelectorProvider"
    },
    {
      "glob": "META-INF/services/java.time.zone.ZoneRulesProvider"
    },
    {
      "glob": "META-INF/services/org.slf4j.spi.SLF4JServiceProvider"
    },
    {
      "glob": "logback-test.scmo"
    },
    {
      "glob": "logback-test.xml"
    },
    {
      "glob": "logback.scmo"
    },
    {
      "glob": "logback.xml"
    },
    {
      "glob": "org/apache/ftpserver/message/FtpStatus.properties"
    }
  ],
  "bundles": [],
  "jni": [
    {
      "type": "io.github.mlpre.SonyFtp",
      "methods": [
        {
          "name": "main",
          "parameterTypes": [
            "java.lang.String[]"
          ]
        }
      ]
    },
    {
      "type": "java.lang.Boolean",
      "methods": [
        {
          "name": "getBoolean",
          "parameterTypes": [
            "java.lang.String"
          ]
        }
      ]
    },
    {
      "type": "sun.launcher.LauncherHelper",
      "fields": [
        {
          "name": "isStaticMain"
        },
        {
          "name": "noArgMain"
        }
      ],
      "methods": [
        {
          "name": "getApplicationClass",
          "parameterTypes": []
        }
      ]
    }
  ]
}